alu.v
module alu8 (
    input  [7:0] A,
    input  [7:0] B,
    input  [3:0] sel,
    output [7:0] Result,
    output       Cout,
    output       Zero,
    output       Overflow 
  );

    wire [8:0] add_ext = {1'b0, A} + {1'b0, B};
    wire [8:0] sub_ext = {1'b0, A} - {1'b0, B};
    wire [15:0] mul_ext = A * B;

    assign Result =
        (sel == 4'b0000) ? add_ext[7:0] :
        (sel == 4'b0001) ? sub_ext[7:0] :
        (sel == 4'b0010) ? (A & B) :
        (sel == 4'b0011) ? (A | B):
        (sel == 4'b0100) ? (A ^ B):
        (sel == 4'b0101) ? ~(A | B):
        (sel == 4'b0110) ? ~(A & B):
        (sel == 4'b0111) ? ~(A ^ B):
        (sel == 4'b1000) ? ~A:
        (sel == 4'b1001) ? (A << 1):
        (sel == 4'b1010) ? (A >> 1):
        (sel == 4'b1011) ? {A[6:0], A[7]}:
        (sel == 4'b1100) ? {A[0], A[7:1]}:
        (sel == 4'b1101) ? mul_ext[7:0]:
        (sel == 4'b1110) ? {7'b0, (A > B)}:
        (sel == 4'b1111) ? {7'b0, (A == B)}:
        8'b0;

    assign Cout = (sel == 4'b0000) ? add_ext[8] :
                  (sel == 4'b0001) ? sub_ext[8] :
                  1'b0;

    assign Zero = (Result == 8'b0) ? 1'b1 : 1'b0;

    assign Overflow =
        (sel == 4'b0000) ? ((A[7] == B[7]) && (Result[7] != A[7])) :
        (sel == 4'b0001) ? ((A[7] != B[7]) && (Result[7] != A[7])) :
        1'b0;

endmodule

alu_tb.v
`timescale 1ns/1ps
 
module alu8_tb;
 
    reg  [7:0] A, B;
    reg  [3:0] sel;
    wire [7:0] Result;
    wire       Cout, Zero, Overflow;
 
    alu8 uut (
        .A(A),
        .B(B),
        .sel(sel),
        .Result(Result),
        .Cout(Cout),
        .Zero(Zero),
        .Overflow(Overflow)
    );
 
    task show;
        input [127:0] opname; // string label
        begin
            $display("%-6s A=%3d(0x%02h) B=%3d(0x%02h) sel=%b -> Result=%3d(0x%02h) Cout=%b Zero=%b Ovf=%b",
                       opname, A, A, B, B, sel, Result, Result, Cout, Zero, Overflow);
        end
    endtask
 
    initial begin
        $dumpfile("alu.vcd");
        $dumpvars(0, alu8_tb);
        $display("================ 8-bit ALU Testbench ================");
 
        A = 8'd45;  B = 8'd15;
 
        sel = 4'b0000; #10; show("ADD");
        sel = 4'b0001; #10; show("SUB");
        sel = 4'b0010; #10; show("AND");
        sel = 4'b0011; #10; show("OR");
        sel = 4'b0100; #10; show("XOR");
        sel = 4'b0101; #10; show("NOR");
        sel = 4'b0110; #10; show("NAND");
        sel = 4'b0111; #10; show("XNOR");
        sel = 4'b1000; #10; show("NOT");
        sel = 4'b1001; #10; show("SLL");
        sel = 4'b1010; #10; show("SRL");
        sel = 4'b1011; #10; show("ROL");
        sel = 4'b1100; #10; show("ROR");
        sel = 4'b1101; #10; show("MUL");
        sel = 4'b1110; #10; show("GT");
        sel = 4'b1111; #10; show("EQ");
 
        $display("-------------------------------------------------------");
        // Edge case: ADD with carry out
        A = 8'hFF; B = 8'h01; sel = 4'b0000; #10; show("ADD");
 
        // Edge case: SUB causing borrow (A < B)
        A = 8'd10; B = 8'd20; sel = 4'b0001; #10; show("SUB");
 
        // Edge case: Zero flag
        A = 8'd0; B = 8'd0; sel = 4'b0011; #10; show("OR(Z)");
 
        // Edge case: signed overflow on ADD (127 + 1 -> -128 in signed)
        A = 8'd127; B = 8'd1; sel = 4'b0000; #10; show("ADD(OVF)");
 
        // Edge case: signed overflow on SUB (-128 - 1 -> overflow)
        A = 8'h80; B = 8'h01; sel = 4'b0001; #10; show("SUB(OVF)");
 
        // Equality check
        A = 8'd99; B = 8'd99; sel = 4'b1111; #10; show("EQ(1)");
 
        $display("========================================================");
        $finish;
    end
 
endmodule

alu.vcd
$date
	Thu Jun 25 21:26:48 2026
$end
$version
	Icarus Verilog
$end
$timescale
	1ps
$end
$scope module alu8_tb $end
$var wire 1 ! Zero $end
$var wire 8 " Result [7:0] $end
$var wire 1 # Overflow $end
$var wire 1 $ Cout $end
$var reg 8 % A [7:0] $end
$var reg 8 & B [7:0] $end
$var reg 4 ' sel [3:0] $end
$scope module uut $end
$var wire 8 ( A [7:0] $end
$var wire 8 ) B [7:0] $end
$var wire 4 * sel [3:0] $end
$var wire 9 + sub_ext [8:0] $end
$var wire 16 , mul_ext [15:0] $end
$var wire 9 - add_ext [8:0] $end
$var wire 1 ! Zero $end
$var wire 8 . Result [7:0] $end
$var wire 1 # Overflow $end
$var wire 1 $ Cout $end
$upscope $end
$scope task show $end
$var reg 128 / opname [127:0] $end
$upscope $end
$upscope $end
$enddefinitions $end
$comment Show the parameter values. $end
$dumpall
$end
#0
$dumpvars
bx /
b111100 .
b111100 -
b1010100011 ,
b11110 +
b0 *
b1111 )
b101101 (
b0 '
b1111 &
b101101 %
0$
0#
b111100 "
0!
$end
#10000
b11110 "
b11110 .
b1 '
b1 *
b10000010100010001000100 /
#20000
b1101 "
b1101 .
b10 '
b10 *
b10100110101010101000010 /
#30000
b101111 "
b101111 .
b11 '
b11 *
b10000010100111001000100 /
#40000
b100010 "
b100010 .
b100 '
b100 *
b100111101010010 /
#50000
b11010000 "
b11010000 .
b101 '
b101 *
b10110000100111101010010 /
#60000
b11110010 "
b11110010 .
b110 '
b110 *
b10011100100111101010010 /
#70000
b11011101 "
b11011101 .
b111 '
b111 *
b1001110010000010100111001000100 /
#80000
b11010010 "
b11010010 .
b1000 '
b1000 *
b1011000010011100100111101010010 /
#90000
b1011010 "
b1011010 .
b1001 '
b1001 *
b10011100100111101010100 /
#100000
b10110 "
b10110 .
b1010 '
b1010 *
b10100110100110001001100 /
#110000
b1011010 "
b1011010 .
b1011 '
b1011 *
b10100110101001001001100 /
#120000
b10010110 "
b10010110 .
b1100 '
b1100 *
b10100100100111101001100 /
#130000
b10100011 "
b10100011 .
b1101 '
b1101 *
b10100100100111101010010 /
#140000
b1 "
b1 .
b1110 '
b1110 *
b10011010101010101001100 /
#150000
1!
b0 "
b0 .
b1111 '
b1111 *
b100011101010100 /
#160000
1$
1!
b0 "
b0 .
b100000000 -
b11111110 +
b11111111 ,
b0 '
b0 *
b1 &
b1 )
b11111111 %
b11111111 (
b100010101010001 /
#170000
0!
b11110110 "
b11110110 .
1$
0#
b11110 -
b111110110 +
b11001000 ,
b1 '
b1 *
b10100 &
b10100 )
b1010 %
b1010 (
b10000010100010001000100 /
#180000
1!
b0 "
b0 .
0$
b0 -
b0 +
b0 ,
b11 '
b11 *
b0 &
b0 )
b0 %
b0 (
b10100110101010101000010 /
#190000
1#
0!
b10000000 "
b10000000 .
b1111111 ,
b10000000 -
b1111110 +
b0 '
b0 *
b1 &
b1 )
b1111111 %
b1111111 (
b100111101010010001010000101101000101001 /
#200000
b1111111 "
b1111111 .
1#
b10000001 -
b1111111 +
b10000000 ,
b1 '
b1 *
b10000000 %
b10000000 (
b100000101000100010001000010100001001111010101100100011000101001 /
#210000
0!
b1 "
b1 .
0#
b11000110 -
b0 +
b10011001001001 ,
b1111 '
b1111 *
b1100011 &
b1100011 )
b1100011 %
b1100011 (
b101001101010101010000100010100001001111010101100100011000101001 /
#220000
b100010101010001001010000011000100101001 /
