cu.v
module cu (
    input         clk,
    input         reset,
    input  [31:0] INSTRUCTION,

    output [2:0]  READREG1,
    output [2:0]  READREG2,
    output [2:0]  WRITEREG,
    output        WRITEENABLE,

    output [7:0]  IMMEDIATE,


    output [2:0]  ALUOP,

    output        MUX1_SEL,   
    output        MUX2_SEL,   


    output reg [31:0] PC
);


    assign IMMEDIATE   = INSTRUCTION[31:24];
    assign ALUOP       = INSTRUCTION[23:21];
    assign MUX2_SEL    = INSTRUCTION[20];
    assign MUX1_SEL    = INSTRUCTION[19];
    assign WRITEENABLE = INSTRUCTION[18];
    assign WRITEREG    = INSTRUCTION[17:15];
    assign READREG1    = INSTRUCTION[14:12];
    assign READREG2    = INSTRUCTION[11:9];

 
    always @(posedge clk or posedge reset) begin
        if (reset)
            PC <= 32'd0;
        else
            PC <= PC + 32'd4;
    end

endmodule

cu_tb.v
`timescale 1ns/1ps

module cu_tb;

    reg         clk;
    reg         reset;
    reg  [31:0] INSTRUCTION;

    wire [2:0]  READREG1;
    wire [2:0]  READREG2;
    wire [2:0]  WRITEREG;
    wire        WRITEENABLE;
    wire [7:0]  IMMEDIATE;
    wire [2:0]  ALUOP;
    wire        MUX1_SEL;
    wire        MUX2_SEL;
    wire [31:0] PC;

    // Instantiate Control Unit
    cu uut (
        .clk(clk),
        .reset(reset),
        .INSTRUCTION(INSTRUCTION),
        .READREG1(READREG1),
        .READREG2(READREG2),
        .WRITEREG(WRITEREG),
        .WRITEENABLE(WRITEENABLE),
        .IMMEDIATE(IMMEDIATE),
        .ALUOP(ALUOP),
        .MUX1_SEL(MUX1_SEL),
        .MUX2_SEL(MUX2_SEL),
        .PC(PC)
    );

    // Clock generation: 10ns period
    always #5 clk = ~clk;

    // Display task
    task show;
        input [127:0] label;
        begin
            $display("%-12s | PC=%0d | ALUOP=%b MUX2=%b MUX1=%b WE=%b | WREG=%0d RREG1=%0d RREG2=%0d | IMM=%0d(0x%02h)",
                     label, PC, ALUOP, MUX2_SEL, MUX1_SEL, WRITEENABLE,
                     WRITEREG, READREG1, READREG2, IMMEDIATE, IMMEDIATE);
        end
    endtask

    // ---------------------------------------------------------------
    // Instruction builder (helper)
    //   imm[7:0], aluop[2:0], mux2, mux1, we, wreg[2:0],
    //   rreg1[2:0], rreg2[2:0], reserved[8:0]
    // ---------------------------------------------------------------
    function [31:0] build_instr;
        input [7:0]  imm;
        input [2:0]  aluop;
        input        mux2;
        input        mux1;
        input        we;
        input [2:0]  wreg;
        input [2:0]  rreg1;
        input [2:0]  rreg2;
        begin
            build_instr = {imm, aluop, mux2, mux1, we, wreg, rreg1, rreg2, 9'b0};
        end
    endfunction

    initial begin
        $dumpfile("cu.vcd");
        $dumpvars(0, cu_tb);
        $display("================== Control Unit Testbench ==================");
        $display("LABEL        | PC   | ALUOP MUX2 MUX1 WE  | WREG RREG1 RREG2 | IMM");
        $display("-------------------------------------------------------------");

        clk = 0;
        reset = 1;
        INSTRUCTION = 32'd0;

        // ---- Reset ----
        #10;
        show("RESET");

        reset = 0;

        // ---- Test 1: ADD R1, R2, R3  (R1 = R2 + R3) ----
        //   imm=0, aluop=000(ADD), mux2=0, mux1=0, we=1,
        //   wreg=1, rreg1=2, rreg2=3
        INSTRUCTION = build_instr(8'd0, 3'b000, 1'b0, 1'b0, 1'b1, 3'd1, 3'd2, 3'd3);
        @(posedge clk); #1;
        show("ADD R1,R2,R3");

        // ---- Test 2: SUB R4, R5, R6  (R4 = R5 - R6) ----
        //   aluop=001(SUB), mux1=1 (2's comp), we=1
        INSTRUCTION = build_instr(8'd0, 3'b001, 1'b0, 1'b1, 1'b1, 3'd4, 3'd5, 3'd6);
        @(posedge clk); #1;
        show("SUB R4,R5,R6");

        // ---- Test 3: AND R0, R1, R2 ----
        //   aluop=010(AND), we=1
        INSTRUCTION = build_instr(8'd0, 3'b010, 1'b0, 1'b0, 1'b1, 3'd0, 3'd1, 3'd2);
        @(posedge clk); #1;
        show("AND R0,R1,R2");

        // ---- Test 4: ADDI R7, R0, #42  (R7 = R0 + 42) ----
        //   imm=42, aluop=000(ADD), mux2=1 (use immediate), we=1
        INSTRUCTION = build_instr(8'd42, 3'b000, 1'b1, 1'b0, 1'b1, 3'd7, 3'd0, 3'd0);
        @(posedge clk); #1;
        show("ADDI R7,R0,42");

        // ---- Test 5: OR R3, R4, R5 ----
        //   aluop=011(OR), we=1
        INSTRUCTION = build_instr(8'd0, 3'b011, 1'b0, 1'b0, 1'b1, 3'd3, 3'd4, 3'd5);
        @(posedge clk); #1;
        show("OR R3,R4,R5");

        // ---- Test 6: XOR R2, R6, R7 ----
        //   aluop=100(XOR), we=1
        INSTRUCTION = build_instr(8'd0, 3'b100, 1'b0, 1'b0, 1'b1, 3'd2, 3'd6, 3'd7);
        @(posedge clk); #1;
        show("XOR R2,R6,R7");

        // ---- Test 7: NOP (no write, all zero) ----
        INSTRUCTION = build_instr(8'd0, 3'b000, 1'b0, 1'b0, 1'b0, 3'd0, 3'd0, 3'd0);
        @(posedge clk); #1;
        show("NOP");

        // ---- Test 8: LOAD IMMEDIATE R5 = 255 ----
        //   imm=255, aluop=000(ADD), mux2=1, we=1, rreg1=0 (R0=0 base)
        INSTRUCTION = build_instr(8'd255, 3'b000, 1'b1, 1'b0, 1'b1, 3'd5, 3'd0, 3'd0);
        @(posedge clk); #1;
        show("LDI R5,255");

        // ---- Verify PC increments ----
        $display("-------------------------------------------------------------");
        $display("Final PC = %0d (expected: %0d after 8 clock edges)", PC, 8*4);

        $display("================== Testbench Complete ==================");
        $finish;
    end

endmodule

cu.vcd
$date
	Thu Jul  2 18:45:02 2026
$end
$version
	Icarus Verilog
$end
$timescale
	1ps
$end
$scope module cu_tb $end
$var wire 3 ! WRITEREG [2:0] $end
$var wire 1 " WRITEENABLE $end
$var wire 3 # READREG2 [2:0] $end
$var wire 3 $ READREG1 [2:0] $end
$var wire 32 % PC [31:0] $end
$var wire 1 & MUX2_SEL $end
$var wire 1 ' MUX1_SEL $end
$var wire 8 ( IMMEDIATE [7:0] $end
$var wire 3 ) ALUOP [2:0] $end
$var reg 32 * INSTRUCTION [31:0] $end
$var reg 1 + clk $end
$var reg 1 , reset $end
$scope function build_instr $end
$var reg 3 - aluop [2:0] $end
$var reg 8 . imm [7:0] $end
$var reg 1 / mux1 $end
$var reg 1 0 mux2 $end
$var reg 3 1 rreg1 [2:0] $end
$var reg 3 2 rreg2 [2:0] $end
$var reg 1 3 we $end
$var reg 3 4 wreg [2:0] $end
$upscope $end
$scope module uut $end
$var wire 32 5 INSTRUCTION [31:0] $end
$var wire 1 + clk $end
$var wire 1 , reset $end
$var wire 3 6 WRITEREG [2:0] $end
$var wire 1 " WRITEENABLE $end
$var wire 3 7 READREG2 [2:0] $end
$var wire 3 8 READREG1 [2:0] $end
$var wire 1 & MUX2_SEL $end
$var wire 1 ' MUX1_SEL $end
$var wire 8 9 IMMEDIATE [7:0] $end
$var wire 3 : ALUOP [2:0] $end
$var reg 32 ; PC [31:0] $end
$upscope $end
$scope task show $end
$var reg 128 < label [127:0] $end
$upscope $end
$upscope $end
$enddefinitions $end
$comment Show the parameter values. $end
$dumpall
$end
#0
$dumpvars
bx <
b0 ;
b0 :
b0 9
b0 8
b0 7
b0 6
b0 5
bx 4
x3
bx 2
bx 1
x0
x/
bx .
bx -
1,
0+
b0 *
b0 )
b0 (
0'
0&
b0 %
b0 $
b0 #
0"
b0 !
$end
#5000
1+
#10000
1"
b1 !
b1 6
b10 $
b10 8
b11 #
b11 7
0+
b1001010011000000000 *
b1001010011000000000 5
b0 .
b0 -
00
0/
13
b1 4
b10 1
b11 2
0,
b101001001000101010100110100010101010100 <
#15000
b100 %
b100 ;
1+
#16000
b1 )
b1 :
1'
b100 !
b100 6
b101 $
b101 8
b110 #
b110 7
b1011100101110000000000 *
b1011100101110000000000 5
b1 -
1/
b100 4
b101 1
b110 2
b10000010100010001000100001000000101001000110001001011000101001000110010001011000101001000110011 <
#20000
0+
#25000
b1000 %
b1000 ;
1+
#26000
b10 )
b10 :
0'
b0 !
b0 6
b1 $
b1 8
b10 #
b10 7
b10001000001010000000000 *
b10001000001010000000000 5
b10 -
0/
b0 4
b1 1
b10 2
b10100110101010101000010001000000101001000110100001011000101001000110101001011000101001000110110 <
#30000
0+
#35000
b1100 %
b1100 ;
1+
#36000
b101010 (
b101010 9
b0 )
b0 :
1&
b111 !
b111 6
b0 $
b0 8
b0 #
b0 7
b101010000101111000000000000000 *
b101010000101111000000000000000 5
b101010 .
b0 -
10
b111 4
b0 1
b0 2
b10000010100111001000100001000000101001000110000001011000101001000110001001011000101001000110010 <
#40000
0+
#45000
b10000 %
b10000 ;
1+
#46000
b0 (
b0 9
b11 )
b11 :
0&
b11 !
b11 6
b100 $
b100 8
b101 #
b101 7
b11001011100101000000000 *
b11001011100101000000000 5
b0 .
b11 -
00
b11 4
b100 1
b101 2
b1000001010001000100010001001001001000000101001000110111001011000101001000110000001011000011010000110010 <
#50000
0+
#55000
b10100 %
b10100 ;
1+
#56000
b100 )
b100 :
b10 !
b10 6
b110 $
b110 8
b111 #
b111 7
b100001010110111000000000 *
b100001010110111000000000 5
b100 -
b10 4
b110 1
b111 2
b100111101010010001000000101001000110011001011000101001000110100001011000101001000110101 <
#60000
0+
#65000
b11000 %
b11000 ;
1+
#66000
b0 )
b0 :
0"
b0 !
b0 6
b0 $
b0 8
b0 #
b0 7
b0 *
b0 5
b0 -
03
b0 4
b0 1
b0 2
b10110000100111101010010001000000101001000110010001011000101001000110110001011000101001000110111 <
#70000
0+
#75000
b11100 %
b11100 ;
1+
#76000
b11111111 (
b11111111 9
1&
1"
b101 !
b101 6
b11111111000101101000000000000000 *
b11111111000101101000000000000000 5
b11111111 .
10
13
b101 4
b10011100100111101010000 <
#80000
0+
#85000
b100000 %
b100000 ;
1+
#86000
b1001100010001000100100100100000010100100011010100101100001100100011010100110101 <
